facilitypython/__init__.py
facilitypython/facility.py
facilitypython-0.11.10.dist-info/LICENSE
facilitypython-0.11.10.dist-info/METADATA
facilitypython-0.11.10.dist-info/WHEEL
facilitypython-0.11.10.dist-info/top_level.txt
facilitypython-0.11.10.dist-info/RECORD
