Metadata-Version: 2.1
Name: facilitypython
Version: 0.11.10
Summary: Supports Facility API Framework web service clients generated by fsdgenpython.
Home-page: https://github.com/FacilityApi/FacilityPython
Author: Peter Venable
Author-email: peter.venable@gmail.com
Classifier: Programming Language :: Python :: 3
Classifier: License :: OSI Approved :: MIT License
Classifier: Operating System :: OS Independent
Requires-Python: >=3.6
License-File: LICENSE
Requires-Dist: requests
Requires-Dist: requests-oauthlib
